nvidia_ace/__init__.py
nvidia_ace/animation_pb2.py
nvidia_ace/animation_pb2.pyi
nvidia_ace/audio_pb2.py
nvidia_ace/audio_pb2.pyi
nvidia_ace/py.typed
nvidia_ace/status_pb2.py
nvidia_ace/status_pb2.pyi
nvidia_ace-1.0.0.dist-info/METADATA
nvidia_ace-1.0.0.dist-info/WHEEL
nvidia_ace-1.0.0.dist-info/licenses/LICENSE
nvidia_ace-1.0.0.dist-info/RECORD
