Metadata-Version: 2.4
Name: nvidia-ace
Version: 1.0.0
Summary: Shared protobuf types for NVIDIA ACE animation system.
Project-URL: Homepage, https://developer.nvidia.com/ace
Project-URL: Documentation, https://docs.nvidia.com/ace/animation-data-format/1.0/index.html
Author-email: NVIDIA ACE <ace-dev@exchange.nvidia.com>
License-Expression: Apache-2.0
License-File: LICENSE
Requires-Python: >=3.8
Requires-Dist: grpcio<=1.67.1
Requires-Dist: protobuf>=5.29.3
